aspen_pysys/__init__.py
aspen_pysys/constants.py
aspen_pysys/setup.py
aspen_pysys/app/__init__.py
aspen_pysys/app/helpers.py
aspen_pysys/app/hysys.py
aspen_pysys/modules/__init__.py
aspen_pysys/modules/module.py
aspen_pysys/modules/module_type.py
aspen_pysys/modules/energy_stream/__init__.py
aspen_pysys/modules/material_stream/__init__.py
aspen_pysys/modules/material_stream/component.py
aspen_pysys/modules/material_stream/composition.py
aspen_pysys/modules/material_stream/stream_props.py
aspen_pysys/modules/unit_operation/__init__.py
aspen_pysys/types/__init__.py
aspen_pysys/types/array.py
aspen_pysys/types/constant.py
aspen_pysys/types/dictionary.py
aspen_pysys/types/non_module.py
aspen_pysys/types/object.py
aspen_pysys/types/object_type.py
aspen_pysys-0.0.10.dist-info/METADATA
aspen_pysys-0.0.10.dist-info/WHEEL
aspen_pysys-0.0.10.dist-info/licenses/LICENSE
aspen_pysys-0.0.10.dist-info/RECORD
