Metadata-Version: 2.4
Name: aspen_pysys
Version: 0.0.10
Summary: Python interface for Aspen HYSYS
Project-URL: Homepage, https://codeberg.org/CacklingTanuki/aspen-pysys
Project-URL: Issues, https://codeberg.org/CacklingTanuki/aspen-pysys/issues
Author-email: Hariidaran Tamilmaran <hariidaran@proton.me>
License-Expression: GPL-3.0-or-later
License-File: LICENSE
Classifier: Operating System :: Microsoft :: Windows :: Windows 11
Classifier: Programming Language :: Python :: 3
Classifier: Topic :: Scientific/Engineering
Requires-Python: >=3.9
